definitions/__init__.py
definitions/__main__.py
definitions/config.py
definitions/custom_scripts/__init__.py
definitions/custom_scripts/operations_groups.py
definitions/custom_scripts/operations_schemas.py
definitions/custom_scripts/operations_tables.py
definitions/custom_scripts/render.py
definitions/custom_scripts/schemas.py
definitions/custom_scripts/tables.py
definitions/templates/definitions/README
definitions/templates/definitions/alembic.ini.mako
definitions/templates/definitions/env.py
definitions/templates/definitions/script.py.mako
definitions_lib-2025.5.1.1.dist-info/licenses/LICENSE
definitions_lib-2025.5.1.1.dist-info/METADATA
definitions_lib-2025.5.1.1.dist-info/WHEEL
definitions_lib-2025.5.1.1.dist-info/top_level.txt
definitions_lib-2025.5.1.1.dist-info/RECORD
