Metadata-Version: 2.4
Name: definitions_lib
Version: 2025.5.1.1
Author: profcomff.com
Author-email: "profcomff.com" <admin@profcomff.com>
License:                                  Apache License
Classifier: Development Status :: 5 - Production/Stable
Classifier: Programming Language :: Python :: 3
Classifier: Programming Language :: Python :: 3.11
Requires-Python: >=3.10
License-File: LICENSE
Requires-Dist: SQLAlchemy
Requires-Dist: psycopg2-binary
Requires-Dist: alembic
Dynamic: author
Dynamic: license-file
Dynamic: requires-python
